benchmarks/__init__.py
benchmarks/benchmarks.py
gnss/__init__.py
gnss/coord_system.py
gnss/gps_time.py
gnss/py.typed
swiftnav_gnss-0.5.1.dist-info/LICENSE
swiftnav_gnss-0.5.1.dist-info/METADATA
swiftnav_gnss-0.5.1.dist-info/WHEEL
swiftnav_gnss-0.5.1.dist-info/top_level.txt
swiftnav_gnss-0.5.1.dist-info/RECORD
