Metadata-Version: 2.1
Name: swiftnav-gnss
Version: 0.5.1
Summary: GNSS Utilities
Home-page: https://github.com/swift-nav/pygnss
Author: Swift Navigation
Author-email: dev@swiftnav.com
License: mit
Classifier: License :: OSI Approved :: MIT License
Classifier: Programming Language :: Python
Classifier: Programming Language :: Python :: 3
Classifier: Programming Language :: Python :: 3.7
License-File: LICENSE
Requires-Dist: numpy (>=1.21)
Requires-Dist: pandas (>=1.0)
Provides-Extra: test
Requires-Dist: pytest ; extra == 'test'
Requires-Dist: hypothesis ; extra == 'test'
Requires-Dist: mypy ; extra == 'test'
Requires-Dist: pandas-stubs ; extra == 'test'
Requires-Dist: black ; extra == 'test'
